Workbook

Sheet Inicio
B3: PROCESOS CLAROS · Test de madurez operativa
B4: ¿Tu empresa está lista para un sistema?
B5: 20 preguntas · 5 áreas · 15 minutos. Antes de implementar un ERP, ordena tu negocio.
B6: Metodología basada en el formato del Systemization Snapshot de ProcessDriven y en su 2025 Small Business Operations Report (4.740 equipos de 158 países), complementada con Churchill y Lewis (Harvard Business Review) y COMPITE para la preparación para un ERP.
B8: Cómo funciona
B9: 1. Ve a la hoja «Test» y completa los datos de tu empresa.
B10: 2. Cada pregunta tiene 4 respuestas que describen situaciones concretas, de la menos a la más ordenada. Elige en la celda amarilla la que describe cómo funciona HOY tu empresa, no cómo debería funcionar.
B11: 3. Si dos respuestas relacionadas no calzan, verás un comentario en la columna «Mirada sistémica». Revísalo con calma: puedes mantener o cambiar tu respuesta.
B12: 4. Mira la hoja «Resultado»: puntaje por área, gráfico, veredicto, por dónde empezar y cómo te comparas con otras pymes.
B14: Ejemplo
B15: «Si la persona más irreemplazable falta un mes sin aviso, la operación…» Si sabes que se harían los despachos pero nadie podría facturar ni cobrar, la respuesta honesta es «Tendría problemas serios».
B17: Preguntas críticas ★
... B25: Celdas amarillas = las completas tú. Todo lo demás se calcula solo.
B27: =HYPERLINK("mailto:jorge@procesosclaros.cl?subject=Resultado%20del%20test%20de%20madurez","¿Quieres revisarlo conmigo? Envíame este archivo completado a jorge@procesosclaros.cl →") -> ¿Quieres revisarlo conmigo? Envíame este archivo completado a jorge@procesosclaros.cl →
B28: Jorge Rivera · jorge@procesosclaros.cl · www.procesosclaros.cl

Sheet Test
A1: Test de madurez operativa
A2: Elige en cada celda amarilla la respuesta que describe cómo funciona HOY tu empresa. ★ = pregunta crítica para un ERP. Si dos respuestas relacionadas no calzan, verás un comentario en «Mirada sistémica».
B4: Empresa
B5: Quién responde (cargo)
B6: Rubro
B7: N° de personas
B8: Fecha
A10: N° | B10: Área | C10: Pregunta | D10: Tu respuesta | E10: Pts | F10: Mirada sistémica
A11: 1. FLUJO Y RESPONSABLES — Quién hace qué, cuándo y cómo, desde que entra un cliente hasta que cobras.
A12: 1 | B12: Flujo y responsables | C12: ¿Está claro el recorrido completo de un pedido, desde que llega el cliente hasta que cobramos? ★ | E12: =IF(D12="","",MATCH(D12,Config!$B$2:$E$2,0)-1) | G12: 1
A13: 2 | B13: Flujo y responsables | C13: ¿Cómo están definidas las responsabilidades en las etapas clave (ventas, compras, bodega, facturación, cobranza)? ★ | E13: =IF(D13="","",MATCH(D13,Config!$B$3:$E$3,0)-1) | F13: =IF(IF(OR($E$12="",$E$13=""),FALSE(),AND($E$12>=3,$E$13<=0)),"Mirada sistémica: en P1 el recorrido del pedido está claro y vigente, pero aquí todos hacen de todo. ¿Quién responde por cada paso de ese recorrido?","") | G13: 1 | H13: =IF(IF(OR($E$12="",$E$13=""),FALSE(),AND($E$12>=3,$E$13<=0)),1,0) -> 0
A14: 3 | B14: Flujo y responsables | C14: ¿Cómo se controlan las tareas que se repiten (cierres, conciliaciones, pedidos a proveedores, inventarios)? | E14: =IF(D14="","",MATCH(D14,Config!$B$4:$E$4,0)-1) | G14: 0
A15: 4 | B15: Flujo y responsables | C15: ¿Cómo sabes en qué etapa está un pedido o trabajo en este momento? | E15: =IF(D15="","",MATCH(D15,Config!$B$5:$E$5,0)-1) | G15: 0
A16: 2. DATOS — Si la información existe una sola vez, es confiable, está en un lugar oficial y las herramientas se usan de verdad.
A17: 5 | B17: Datos | C17: ¿Dónde está la información oficial de clientes, productos y precios? ★ | E17: =IF(D17="","",MATCH(D17,Config!$B$6:$E$6,0)-1) | G17: 1
A18: 6 | B18: Datos | C18: ¿El stock registrado coincide con lo que hay en bodega? (Si no manejas stock, piensa en insumos o en horas vendidas vs. registradas.) | E18: =IF(D18="","",MATCH(D18,Config!$B$7:$E$7,0)-1) | G18: 0
A19: 7 | B19: Datos | C19: ¿Cuántas veces se digita un mismo dato (un pedido, una factura, un cliente)? | E19: =IF(D19="","",MATCH(D19,Config!$B$8:$E$8,0)-1) | F19: =IF(IF(OR($E$19="",$E$17=""),FALSE(),$E$19-$E$17>=2),"Mirada sistémica: dices que cada dato se digita una sola vez, pero en P5 conviven varias versiones de clientes, productos o precios. ¿Cómo se mantienen iguales sin volver a digitarlos?","") | G19: 0 | H19: =IF(IF(OR($E$19="",$E$17=""),FALSE(),$E$19-$E$17>=2),1,0) -> 0
A20: 8 | B20: Datos | C20: Las herramientas que ya usan (software o planillas compartidas), ¿cómo se usan? | E20: =IF(D20="","",MATCH(D20,Config!$B$9:$E$9,0)-1) | F20: =IF(IF(OR($E$15="",$E$20=""),FALSE(),$E$15-$E$20>=2),"Mirada sistémica: en P4 indicaste que ves el trabajo en un solo lugar, y aquí que las herramientas compartidas casi no se usan. ¿Dónde está ese «solo lugar»?","")&IF(AND(IF(OR($E$15="",$E$20=""),FALSE(),$E$15-$E$20>=2),IF(OR($E$14="",$E$20=""),FALSE(),$E$14-$E$20>=2)),CHAR(10),"")&IF(IF(OR($E$14="",$E$20=""),FALSE(),$E$14-$E$20>=2),"Mirada sistémica: en P3 indicaste que las tareas rutinarias están en un lugar compartido. ¿Cuál es, si casi no se usan herramientas compartidas?","") | G20: 0 | H20: =IF(IF(OR($E$15="",$E$20=""),FALSE(),$E$15-$E$20>=2),1,0)+IF(IF(OR($E$14="",$E$20=""),FALSE(),$E$14-$E$20>=2),1,0) -> 0
A21: 3. EXCEPCIONES Y CONTROL — Qué pasa cuando algo sale mal, cada cuánto pasa, y si los errores se previenen.
A22: 9 | B22: Excepciones y control | C22: Ante situaciones típicas (devolución, quiebre de stock, pedido urgente, error de factura), ¿qué pasa? ★ | E22: =IF(D22="","",MATCH(D22,Config!$B$10:$E$10,0)-1) | G22: 1
A23: 10 | B23: Excepciones y control | C23: ¿Con qué frecuencia un error, un problema o un pedido inusual desarma la planificación del día? | E23: =IF(D23="","",MATCH(D23,Config!$B$11:$E$11,0)-1) | G23: 0
A24: 11 | B24: Excepciones y control | C24: Cuando ocurre un error, normalmente… | E24: =IF(D24="","",MATCH(D24,Config!$B$12:$E$12,0)-1) | G24: 0
A25: 12 | B25: Excepciones y control | C25: ¿Hay límites y aprobaciones claras (descuentos, compras, crédito a clientes)? | E25: =IF(D25="","",MATCH(D25,Config!$B$13:$E$13,0)-1) | G25: 0
A26: 4. RECURSOS Y MEDICIÓN — Dónde se van el tiempo y el dinero: márgenes, caja, indicadores y tiempo para mejorar.
A27: 13 | B27: Recursos y medición | C27: ¿Conocen el margen real por producto, servicio o línea de negocio? | E27: =IF(D27="","",MATCH(D27,Config!$B$14:$E$14,0)-1) | F27: =IF(IF(OR($E$27="",$E$17=""),FALSE(),AND($E$27>=3,$E$17<=0)),"Mirada sistémica: conoces el margen de todos tus productos, pero en P5 los precios están en varios Excel personales. ¿Con cuál versión lo calculas?","") | G27: 0 | H27: =IF(IF(OR($E$27="",$E$17=""),FALSE(),AND($E$27>=3,$E$17<=0)),1,0) -> 0
A28: 14 | B28: Recursos y medición | C28: ¿Cómo manejan la caja? | E28: =IF(D28="","",MATCH(D28,Config!$B$15:$E$15,0)-1) | F28: =IF(IF(OR($E$28="",$E$18=""),FALSE(),AND($E$28>=3,$E$18<=1)),"Mirada sistémica: tu flujo de caja incluye el inventario, pero en P6 el stock no se revisa o no cuadra. ¿Qué tan confiable es esa cifra?","") | G28: 0 | H28: =IF(IF(OR($E$28="",$E$18=""),FALSE(),AND($E$28>=3,$E$18<=1)),1,0) -> 0
A29: 15 | B29: Recursos y medición | C29: ¿Qué indicadores de la operación miden? | E29: =IF(D29="","",MATCH(D29,Config!$B$16:$E$16,0)-1) | F29: =IF(IF(OR($E$29="",$E$17=""),FALSE(),AND($E$29>=3,$E$17<=0)),"Mirada sistémica: mides indicadores con meta, pero en P5 la información oficial está repartida en varios Excel. ¿De dónde salen esos datos?","") | G29: 0 | H29: =IF(IF(OR($E$29="",$E$17=""),FALSE(),AND($E$29>=3,$E$17<=0)),1,0) -> 0
A30: 16 | B30: Recursos y medición | C30: ¿En qué se va la mayor parte del tiempo del equipo? | E30: =IF(D30="","",MATCH(D30,Config!$B$17:$E$17,0)-1) | F30: =IF(IF(OR($E$23="",$E$30=""),FALSE(),AND($E$23>=2,$E$30<=0)),"Mirada sistémica: en P10 los imprevistos son poco frecuentes, pero aquí el tiempo se va apagando incendios. ¿Qué ocupa realmente el día del equipo?","")&IF(AND(IF(OR($E$23="",$E$30=""),FALSE(),AND($E$23>=2,$E$30<=0)),IF(OR($E$30="",$E$23=""),FALSE(),AND($E$30>=3,$E$23<=0))),CHAR(10),"")&IF(IF(OR($E$30="",$E$23=""),FALSE(),AND($E$30>=3,$E$23<=0)),"Mirada sistémica: en P10 indicaste imprevistos a diario, y aquí tiempo reservado para mejorar. Si es así, ¡muy bien! Si no, vale la pena revisar una de las dos.","") | G30: 0 | H30: =IF(IF(OR($E$23="",$E$30=""),FALSE(),AND($E$23>=2,$E$30<=0)),1,0)+IF(IF(OR($E$30="",$E$23=""),FALSE(),AND($E$30>=3,$E$23<=0)),1,0) -> 0
A31: 5. DOCUMENTACIÓN Y EQUIPO — Si la operación funciona sin depender de una persona y el equipo participa en el cambio.
A32: 17 | B32: Documentación y equipo | C32: ¿Dónde están descritos los procesos clave (instructivos, procedimientos)? | E32: =IF(D32="","",MATCH(D32,Config!$B$18:$E$18,0)-1) | F32: =IF(IF(OR($E$32="",$E$14=""),FALSE(),AND($E$32>=3,$E$14<=1)),"Mirada sistémica: los procesos están documentados y al día, pero en P3 las tareas rutinarias se llevan de memoria o en listas personales. ¿Esos documentos se usan en el día a día?","") | G32: 0 | H32: =IF(IF(OR($E$32="",$E$14=""),FALSE(),AND($E$32>=3,$E$14<=1)),1,0) -> 0
A33: 18 | B33: Documentación y equipo | C33: Si la persona más irreemplazable falta un mes sin aviso, la operación… | E33: =IF(D33="","",MATCH(D33,Config!$B$19:$E$19,0)-1) | F33: =IF(IF(OR($E$33="",$E$32=""),FALSE(),AND($E$33>=3,$E$32<=1)),"Mirada sistémica: la operación seguiría sin tu persona clave, pero en P17 los procesos no están descritos en un lugar común. ¿Dónde queda lo que esa persona sabe?","")&IF(AND(IF(OR($E$33="",$E$32=""),FALSE(),AND($E$33>=3,$E$32<=1)),IF(OR($E$33="",$E$13=""),FALSE(),AND($E$33>=3,$E$13<=1))),CHAR(10),"")&IF(IF(OR($E$33="",$E$13=""),FALSE(),AND($E$33>=3,$E$13<=1)),"Mirada sistémica: en P2 las responsabilidades no están definidas por escrito. Sin eso, ¿quién sabría qué cubrir si falta la persona clave?","") | G33: 0 | H33: =IF(IF(OR($E$33="",$E$32=""),FALSE(),AND($E$33>=3,$E$32<=1)),1,0)+IF(IF(OR($E$33="",$E$13=""),FALSE(),AND($E$33>=3,$E$13<=1)),1,0) -> 0
A34: 19 | B34: Documentación y equipo | C34: ¿Quién toma las decisiones del día a día? | E34: =IF(D34="","",MATCH(D34,Config!$B$20:$E$20,0)-1) | F34: =IF(IF(OR($E$34="",$E$22=""),FALSE(),AND($E$34>=3,$E$22<=1)),"Mirada sistémica: el equipo decide dentro de reglas claras, pero en P9 las situaciones típicas se resuelven sin una forma acordada. ¿Qué reglas usa al decidir?","")&IF(AND(IF(OR($E$34="",$E$22=""),FALSE(),AND($E$34>=3,$E$22<=1)),IF(OR($E$34="",$E$25=""),FALSE(),AND($E$34>=3,$E$25<=1))),CHAR(10),"")&IF(IF(OR($E$34="",$E$25=""),FALSE(),AND($E$34>=3,$E$25<=1)),"Mirada sistémica: el equipo decide dentro de reglas, pero en P12 los límites y aprobaciones no existen o se saltan. ¿Hasta dónde puede decidir?","") | G34: 0 | H34: =IF(IF(OR($E$34="",$E$22=""),FALSE(),AND($E$34>=3,$E$22<=1)),1,0)+IF(IF(OR($E$34="",$E$25=""),FALSE(),AND($E$34>=3,$E$25<=1)),1,0) -> 0
A35: 20 | B35: Documentación y equipo | C35: ¿Cómo participa el equipo en mejorar la forma de trabajar? | E35: =IF(D35="","",MATCH(D35,Config!$B$21:$E$21,0)-1) | F35: =IF(IF(OR($E$35="",$E$34=""),FALSE(),AND($E$35>=3,$E$34<=0)),"Mirada sistémica: el equipo participa en definir procesos, pero en P19 el dueño decide casi todo. ¿Cómo conviven ambas cosas?","") | G35: 0 | H35: =IF(IF(OR($E$35="",$E$34=""),FALSE(),AND($E$35>=3,$E$34<=0)),1,0) -> 0
C37: Preguntas respondidas | D37: =COUNTA(D12:D35)&" de 20" -> 0 de 20
C38: Puntaje total (máx. 60) | D38: =SUM(E12:E35) -> 0
C39: =HYPERLINK("#Resultado!A1","Ver mi resultado →") -> Ver mi resultado →
A41: Sobre «Mirada sistémica»: en una empresa todo está conectado, así que algunas respuestas dependen de otras. Cuando dos respuestas relacionadas parecen no calzar, aparece un comentario. No es un error ni cambia tu puntaje: es una invitación a mirar ambas preguntas juntas. Si tu respuesta refleja la realidad, mantenla.

Sheet Resultado
B2: Tu resultado
B3: =IF(Test!C4="","Completa el nombre de tu empresa en la hoja Test",Test!C4) -> Completa el nombre de tu empresa en la hoja Test
B5: Área | C5: Puntaje | D5: % madurez | E5: Qué mide
B6: Flujo y responsables | C6: =SUMIF(Test!$B$12:$B$35,B6,Test!$E$12:$E$35)&" / 12" -> 0 / 12 | D6: =SUMIF(Test!$B$12:$B$35,B6,Test!$E$12:$E$35)/12 -> 0 | E6: Quién hace qué, cuándo y cómo, desde que entra un cliente hasta que cobras. | G6: =D6+ROW()/100000 -> 6e-05
B7: Datos | C7: =SUMIF(Test!$B$12:$B$35,B7,Test!$E$12:$E$35)&" / 12" -> 0 / 12 | D7: =SUMIF(Test!$B$12:$B$35,B7,Test!$E$12:$E$35)/12 -> 0 | E7: Si la información existe una sola vez, es confiable, está en un lugar oficial y las herramientas se usan de verdad. | G7: =D7+ROW()/100000 -> 7e-05
B8: Excepciones y control | C8: =SUMIF(Test!$B$12:$B$35,B8,Test!$E$12:$E$35)&" / 12" -> 0 / 12 | D8: =SUMIF(Test!$B$12:$B$35,B8,Test!$E$12:$E$35)/12 -> 0 | E8: Qué pasa cuando algo sale mal, cada cuánto pasa, y si los errores se previenen. | G8: =D8+ROW()/100000 -> 8e-05
B9: Recursos y medición | C9: =SUMIF(Test!$B$12:$B$35,B9,Test!$E$12:$E$35)&" / 12" -> 0 / 12 | D9: =SUMIF(Test!$B$12:$B$35,B9,Test!$E$12:$E$35)/12 -> 0 | E9: Dónde se van el tiempo y el dinero: márgenes, caja, indicadores y tiempo para mejorar. | G9: =D9+ROW()/100000 -> 9e-05
B10: Documentación y equipo | C10: =SUMIF(Test!$B$12:$B$35,B10,Test!$E$12:$E$35)&" / 12" -> 0 / 12 | D10: =SUMIF(Test!$B$12:$B$35,B10,Test!$E$12:$E$35)/12 -> 0 | E10: Si la operación funciona sin depender de una persona y el equipo participa en el cambio. | G10: =D10+ROW()/100000 -> 0.0001
B12: TOTAL | C12: =SUM(Test!$E$12:$E$35)&" / 60" -> 0 / 60 | D12: =SUM(Test!$E$12:$E$35)/60 -> 0 | E12: =COUNTA(Test!$D$12:$D$35)&" de 20 preguntas respondidas" -> 0 de 20 preguntas respondidas | H12: =SUMPRODUCT((Test!$G$12:$G$35=1)*(Test!$D$12:$D$35<>"")*(Test!$E$12:$E$35=0)) -> 0
H13: =SUM(Test!$H$12:$H$35) -> 0
B14: VEREDICTO
B15: =IF(COUNTA(Test!$D$12:$D$35)<20,"FALTAN "&(20-COUNTA(Test!$D$12:$D$35))&" RESPUESTAS",IF(AND(D12>=Config!$M$2,MIN(D6:D10)>=Config!$M$4,$H$12=0),"LISTA PARA UN SISTEMA",IF(D12>=Config!$M$3,"ZONA INTERMEDIA","TODAVÍA NO"))) -> FALTAN 20 RESPUESTAS
B16: =IF(B15="LISTA PARA UN SISTEMA","Tu operación tiene reglas, datos y responsables suficientemente claros para que un software los ejecute. El riesgo ahora está en elegir bien: define tus requerimientos reales antes de hablar con proveedores.",IF(B15="ZONA INTERMEDIA",IF(D12>=Config!$M$2,IF($H$12>0,"Tu puntaje total es alto, pero tienes "&$H$12&" pregunta(s) crítica(s) ★ en cero. Sin eso resuelto, un ERP no tiene sobre qué funcionar: es lo primero que hay que ordenar.","Tu puntaje total es alto, pero al menos un área está bajo el 50%. Una cadena es tan fuerte como su eslabón más débil: ordena esa área antes de digitalizar, o el sistema amplificará justo ese problema."),"Tienes bases, pero hay áreas que un sistema no podrá resolver por ti. Si implementas hoy, el software va a automatizar parte del desorden. Ordenar primero las dos áreas más débiles reduce mucho ese riesgo."),IF(B15="TODAVÍA NO","Hoy la operación depende de personas y memoria más que de reglas. Un ERP en este punto probablemente acelere el desorden. La buena noticia: las primeras acciones son simples y no requieren comprar nada.","Responde las 20 preguntas en la hoja Test para ver tu veredicto."))) -> Responde las 20 preguntas en la hoja Test para ver tu veredicto.
B18: =IF($H$13=0,"","Para revisar: "&$H$13&IF($H$13=1," par de respuestas relacionadas no calza"," pares de respuestas relacionadas no calzan")&" entre sí. Mira los comentarios de la columna «Mirada sistémica» en la hoja Test: puedes mantener o ajustar tus respuestas.")
B19: =IF(OR(COUNTA(Test!$D$12:$D$35)<20,NOT(ISNUMBER(Test!C7))),"",IF(Test!C7<10,"Contexto por tamaño: con menos de 10 personas es normal puntuar bajo en indicadores y documentación. Prioriza el flujo del pedido y la fuente única de datos.",IF(Test!C7>=50,"Contexto por tamaño: con 50 o más personas, la dependencia de personas clave y la falta de visibilidad del trabajo pesan mucho más. Dale especial peso a esas preguntas.","")))
B20: POR DÓNDE EMPEZAR
B21: =IF(OR(COUNTA(Test!$D$12:$D$35)<20,B15="LISTA PARA UN SISTEMA"),"","Paso 0, para todos") | C21: =IF(OR(COUNTA(Test!$D$12:$D$35)<20,B15="LISTA PARA UN SISTEMA"),"","Durante 30 días, anota cada error o imprevisto en una planilla compartida: qué pasó, cómo se resolvió y una acción para que no se repita. Es el primer sistema recomendado para empresas que viven apagando incendios, y te da datos reales de dónde está el desorden.")
B22: =IF(COUNTA(Test!$D$12:$D$35)=0,"—",INDEX($B$6:$B$10,MATCH(SMALL($G$6:$G$10,1),$G$6:$G$10,0))) -> — | C22: =IF(COUNTA(Test!$D$12:$D$35)=0,"",INDEX($D$6:$D$10,MATCH(SMALL($G$6:$G$10,1),$G$6:$G$10,0))) | D22: =IF(COUNTA(Test!$D$12:$D$35)=0,"",INDEX(Config!$J$2:$J$6,MATCH(B22,Config!$H$2:$H$6,0)))
B23: Área débil n° 1 · primera acción →
B24: =IF(COUNTA(Test!$D$12:$D$35)=0,"—",INDEX($B$6:$B$10,MATCH(SMALL($G$6:$G$10,2),$G$6:$G$10,0))) -> — | C24: =IF(COUNTA(Test!$D$12:$D$35)=0,"",INDEX($D$6:$D$10,MATCH(SMALL($G$6:$G$10,2),$G$6:$G$10,0))) | D24: =IF(COUNTA(Test!$D$12:$D$35)=0,"",INDEX(Config!$J$2:$J$6,MATCH(B24,Config!$H$2:$H$6,0)))
B25: Área débil n° 2 · primera acción →
B27: =HYPERLINK("https://www.procesosclaros.cl/contacto","¿Quieres revisar este resultado conmigo? Agenda el diagnóstico gratuito de 30 minutos →") -> ¿Quieres revisar este resultado conmigo? Agenda el diagnóstico gratuito de 30 minutos →
B30: CÓMO TE COMPARAS CON OTRAS PYMES
B31: Tema | C31: Tu nivel | D31: Cómo responden otras pymes (ProcessDriven, 2025)
B32: 2. Responsabilidades | C32: =IF(Test!E13="","—",Test!E13&" / 3") -> — | D32: Solo 24,8% de los equipos tiene sus responsabilidades por escrito; 24,4% opera con «cada persona es responsable de todo».
B33: 3. Tareas rutinarias | C33: =IF(Test!E14="","—",Test!E14&" / 3") -> — | D33: Solo 21,1% registra sus tareas rutinarias; 78,9% las lleva de memoria.
B34: 4. Visibilidad del trabajo | C34: =IF(Test!E15="","—",Test!E15&" / 3") -> — | D34: 50,4% solo lo sabe conversando; 27,6% revisando varios lugares; 21,9% lo ve todo en un solo lugar.
B35: 8. Uso de herramientas | C35: =IF(Test!E20="","—",Test!E20&" / 3") -> — | D35: 41,5% dice que todo su equipo usa software de tareas, pero solo 21,9% logra ver todo el trabajo en un solo lugar.
B36: 10. Imprevistos | C36: =IF(Test!E23="","—",Test!E23&" / 3") -> — | D36: 52,5% lo vive al menos varias veces por semana; 16,7% a diario.
B37: 11. Manejo de errores | C37: =IF(Test!E24="","—",Test!E24&" / 3") -> — | D37: 49,4% solo lo arregla; 41,5% además previene; solo 21,0% registra sus errores.
B38: 16. Tiempo para mejorar | C38: =IF(Test!E30="","—",Test!E30&" / 3") -> — | D38: 17,3% dedica la mayor parte del tiempo a arreglar errores; en 66,0% de los equipos, mejorar es a lo que menos tiempo se dedica.
B39: 17. Documentación | C39: =IF(Test!E32="","—",Test!E32&" / 3") -> — | D39: Solo 17,6% guarda sus procedimientos en un lugar accesible, centralizado, editable y seguro.
B40: 18. Persona clave | C40: =IF(Test!E33="","—",Test!E33&" / 3") -> — | D40: 22,1% se detendría; 59,0% tendría problemas pero haría lo esencial; solo 19,0% seguiría funcionando.
B41: 20. Ideas del equipo | C41: =IF(Test!E35="","—",Test!E35&" / 3") -> — | D41: Solo 17,8% tiene un lugar donde guardar ideas y retroalimentación para revisarlas después.
B43: Fuente: ProcessDriven's 2025 Small Business Operations Report — https://processdriven.co/report (4.740 equipos). Comparación aproximada: las alternativas están adaptadas.
B44: Este test es una autoevaluación orientativa: no reemplaza un diagnóstico en terreno.

Sheet Comparar equipo
A1: Comparar respuestas del equipo
A2: Que 2 o 3 personas respondan por separado y anoten aquí sus respuestas. Donde la diferencia es grande, hay algo que conversar.
C4: Nombre → | D4: Persona 1 | E4: Persona 2 | F4: Persona 3
A6: N° | B6: Área | C6: Pregunta | D6: =D4 -> Persona 1 | E6: =E4 -> Persona 2 | F6: =F4 -> Persona 3 | G6: P1 | H6: P2 | I6: P3 | J6: Diferencia | K6: Alerta
A7: 1 | B7: Flujo y responsables | C7: ¿Está claro el recorrido completo de un pedido, desde que llega el cliente hasta que cobramos? ★ | G7: =IF(D7="","",MATCH(D7,Config!$B$2:$E$2,0)-1) | H7: =IF(E7="","",MATCH(E7,Config!$B$2:$E$2,0)-1) | I7: =IF(F7="","",MATCH(F7,Config!$B$2:$E$2,0)-1) | J7: =IF(COUNT(G7:I7)<2,"",MAX(G7:I7)-MIN(G7:I7)) | K7: =IF(J7="","",IF(J7>=Config!$M$5,"Conversar",""))
A8: 2 | B8: Flujo y responsables | C8: ¿Cómo están definidas las responsabilidades en las etapas clave (ventas, compras, bodega, facturación, cobranza)? ★ | G8: =IF(D8="","",MATCH(D8,Config!$B$3:$E$3,0)-1) | H8: =IF(E8="","",MATCH(E8,Config!$B$3:$E$3,0)-1) | I8: =IF(F8="","",MATCH(F8,Config!$B$3:$E$3,0)-1) | J8: =IF(COUNT(G8:I8)<2,"",MAX(G8:I8)-MIN(G8:I8)) | K8: =IF(J8="","",IF(J8>=Config!$M$5,"Conversar",""))
A9: 3 | B9: Flujo y responsables | C9: ¿Cómo se controlan las tareas que se repiten (cierres, conciliaciones, pedidos a proveedores, inventarios)? | G9: =IF(D9="","",MATCH(D9,Config!$B$4:$E$4,0)-1) | H9: =IF(E9="","",MATCH(E9,Config!$B$4:$E$4,0)-1) | I9: =IF(F9="","",MATCH(F9,Config!$B$4:$E$4,0)-1) | J9: =IF(COUNT(G9:I9)<2,"",MAX(G9:I9)-MIN(G9:I9)) | K9: =IF(J9="","",IF(J9>=Config!$M$5,"Conversar",""))
A10: 4 | B10: Flujo y responsables | C10: ¿Cómo sabes en qué etapa está un pedido o trabajo en este momento? | G10: =IF(D10="","",MATCH(D10,Config!$B$5:$E$5,0)-1) | H10: =IF(E10="","",MATCH(E10,Config!$B$5:$E$5,0)-1) | I10: =IF(F10="","",MATCH(F10,Config!$B$5:$E$5,0)-1) | J10: =IF(COUNT(G10:I10)<2,"",MAX(G10:I10)-MIN(G10:I10)) | K10: =IF(J10="","",IF(J10>=Config!$M$5,"Conversar",""))
A11: 5 | B11: Datos | C11: ¿Dónde está la información oficial de clientes, productos y precios? ★ | G11: =IF(D11="","",MATCH(D11,Config!$B$6:$E$6,0)-1) | H11: =IF(E11="","",MATCH(E11,Config!$B$6:$E$6,0)-1) | I11: =IF(F11="","",MATCH(F11,Config!$B$6:$E$6,0)-1) | J11: =IF(COUNT(G11:I11)<2,"",MAX(G11:I11)-MIN(G11:I11)) | K11: =IF(J11="","",IF(J11>=Config!$M$5,"Conversar",""))
A12: 6 | B12: Datos | C12: ¿El stock registrado coincide con lo que hay en bodega? (Si no manejas stock, piensa en insumos o en horas vendidas vs. registradas.) | G12: =IF(D12="","",MATCH(D12,Config!$B$7:$E$7,0)-1) | H12: =IF(E12="","",MATCH(E12,Config!$B$7:$E$7,0)-1) | I12: =IF(F12="","",MATCH(F12,Config!$B$7:$E$7,0)-1) | J12: =IF(COUNT(G12:I12)<2,"",MAX(G12:I12)-MIN(G12:I12)) | K12: =IF(J12="","",IF(J12>=Config!$M$5,"Conversar",""))
A13: 7 | B13: Datos | C13: ¿Cuántas veces se digita un mismo dato (un pedido, una factura, un cliente)? | G13: =IF(D13="","",MATCH(D13,Config!$B$8:$E$8,0)-1) | H13: =IF(E13="","",MATCH(E13,Config!$B$8:$E$8,0)-1) | I13: =IF(F13="","",MATCH(F13,Config!$B$8:$E$8,0)-1) | J13: =IF(COUNT(G13:I13)<2,"",MAX(G13:I13)-MIN(G13:I13)) | K13: =IF(J13="","",IF(J13>=Config!$M$5,"Conversar",""))
A14: 8 | B14: Datos | C14: Las herramientas que ya usan (software o planillas compartidas), ¿cómo se usan? | G14: =IF(D14="","",MATCH(D14,Config!$B$9:$E$9,0)-1) | H14: =IF(E14="","",MATCH(E14,Config!$B$9:$E$9,0)-1) | I14: =IF(F14="","",MATCH(F14,Config!$B$9:$E$9,0)-1) | J14: =IF(COUNT(G14:I14)<2,"",MAX(G14:I14)-MIN(G14:I14)) | K14: =IF(J14="","",IF(J14>=Config!$M$5,"Conversar",""))
A15: 9 | B15: Excepciones y control | C15: Ante situaciones típicas (devolución, quiebre de stock, pedido urgente, error de factura), ¿qué pasa? ★ | G15: =IF(D15="","",MATCH(D15,Config!$B$10:$E$10,0)-1) | H15: =IF(E15="","",MATCH(E15,Config!$B$10:$E$10,0)-1) | I15: =IF(F15="","",MATCH(F15,Config!$B$10:$E$10,0)-1) | J15: =IF(COUNT(G15:I15)<2,"",MAX(G15:I15)-MIN(G15:I15)) | K15: =IF(J15="","",IF(J15>=Config!$M$5,"Conversar",""))
A16: 10 | B16: Excepciones y control | C16: ¿Con qué frecuencia un error, un problema o un pedido inusual desarma la planificación del día? | G16: =IF(D16="","",MATCH(D16,Config!$B$11:$E$11,0)-1) | H16: =IF(E16="","",MATCH(E16,Config!$B$11:$E$11,0)-1) | I16: =IF(F16="","",MATCH(F16,Config!$B$11:$E$11,0)-1) | J16: =IF(COUNT(G16:I16)<2,"",MAX(G16:I16)-MIN(G16:I16)) | K16: =IF(J16="","",IF(J16>=Config!$M$5,"Conversar",""))
A17: 11 | B17: Excepciones y control | C17: Cuando ocurre un error, normalmente… | G17: =IF(D17="","",MATCH(D17,Config!$B$12:$E$12,0)-1) | H17: =IF(E17="","",MATCH(E17,Config!$B$12:$E$12,0)-1) | I17: =IF(F17="","",MATCH(F17,Config!$B$12:$E$12,0)-1) | J17: =IF(COUNT(G17:I17)<2,"",MAX(G17:I17)-MIN(G17:I17)) | K17: =IF(J17="","",IF(J17>=Config!$M$5,"Conversar",""))
A18: 12 | B18: Excepciones y control | C18: ¿Hay límites y aprobaciones claras (descuentos, compras, crédito a clientes)? | G18: =IF(D18="","",MATCH(D18,Config!$B$13:$E$13,0)-1) | H18: =IF(E18="","",MATCH(E18,Config!$B$13:$E$13,0)-1) | I18: =IF(F18="","",MATCH(F18,Config!$B$13:$E$13,0)-1) | J18: =IF(COUNT(G18:I18)<2,"",MAX(G18:I18)-MIN(G18:I18)) | K18: =IF(J18="","",IF(J18>=Config!$M$5,"Conversar",""))
A19: 13 | B19: Recursos y medición | C19: ¿Conocen el margen real por producto, servicio o línea de negocio? | G19: =IF(D19="","",MATCH(D19,Config!$B$14:$E$14,0)-1) | H19: =IF(E19="","",MATCH(E19,Config!$B$14:$E$14,0)-1) | I19: =IF(F19="","",MATCH(F19,Config!$B$14:$E$14,0)-1) | J19: =IF(COUNT(G19:I19)<2,"",MAX(G19:I19)-MIN(G19:I19)) | K19: =IF(J19="","",IF(J19>=Config!$M$5,"Conversar",""))
A20: 14 | B20: Recursos y medición | C20: ¿Cómo manejan la caja? | G20: =IF(D20="","",MATCH(D20,Config!$B$15:$E$15,0)-1) | H20: =IF(E20="","",MATCH(E20,Config!$B$15:$E$15,0)-1) | I20: =IF(F20="","",MATCH(F20,Config!$B$15:$E$15,0)-1) | J20: =IF(COUNT(G20:I20)<2,"",MAX(G20:I20)-MIN(G20:I20)) | K20: =IF(J20="","",IF(J20>=Config!$M$5,"Conversar",""))
A21: 15 | B21: Recursos y medición | C21: ¿Qué indicadores de la operación miden? | G21: =IF(D21="","",MATCH(D21,Config!$B$16:$E$16,0)-1) | H21: =IF(E21="","",MATCH(E21,Config!$B$16:$E$16,0)-1) | I21: =IF(F21="","",MATCH(F21,Config!$B$16:$E$16,0)-1) | J21: =IF(COUNT(G21:I21)<2,"",MAX(G21:I21)-MIN(G21:I21)) | K21: =IF(J21="","",IF(J21>=Config!$M$5,"Conversar",""))
A22: 16 | B22: Recursos y medición | C22: ¿En qué se va la mayor parte del tiempo del equipo? | G22: =IF(D22="","",MATCH(D22,Config!$B$17:$E$17,0)-1) | H22: =IF(E22="","",MATCH(E22,Config!$B$17:$E$17,0)-1) | I22: =IF(F22="","",MATCH(F22,Config!$B$17:$E$17,0)-1) | J22: =IF(COUNT(G22:I22)<2,"",MAX(G22:I22)-MIN(G22:I22)) | K22: =IF(J22="","",IF(J22>=Config!$M$5,"Conversar",""))
A23: 17 | B23: Documentación y equipo | C23: ¿Dónde están descritos los procesos clave (instructivos, procedimientos)? | G23: =IF(D23="","",MATCH(D23,Config!$B$18:$E$18,0)-1) | H23: =IF(E23="","",MATCH(E23,Config!$B$18:$E$18,0)-1) | I23: =IF(F23="","",MATCH(F23,Config!$B$18:$E$18,0)-1) | J23: =IF(COUNT(G23:I23)<2,"",MAX(G23:I23)-MIN(G23:I23)) | K23: =IF(J23="","",IF(J23>=Config!$M$5,"Conversar",""))
A24: 18 | B24: Documentación y equipo | C24: Si la persona más irreemplazable falta un mes sin aviso, la operación… | G24: =IF(D24="","",MATCH(D24,Config!$B$19:$E$19,0)-1) | H24: =IF(E24="","",MATCH(E24,Config!$B$19:$E$19,0)-1) | I24: =IF(F24="","",MATCH(F24,Config!$B$19:$E$19,0)-1) | J24: =IF(COUNT(G24:I24)<2,"",MAX(G24:I24)-MIN(G24:I24)) | K24: =IF(J24="","",IF(J24>=Config!$M$5,"Conversar",""))
A25: 19 | B25: Documentación y equipo | C25: ¿Quién toma las decisiones del día a día? | G25: =IF(D25="","",MATCH(D25,Config!$B$20:$E$20,0)-1) | H25: =IF(E25="","",MATCH(E25,Config!$B$20:$E$20,0)-1) | I25: =IF(F25="","",MATCH(F25,Config!$B$20:$E$20,0)-1) | J25: =IF(COUNT(G25:I25)<2,"",MAX(G25:I25)-MIN(G25:I25)) | K25: =IF(J25="","",IF(J25>=Config!$M$5,"Conversar",""))
A26: 20 | B26: Documentación y equipo | C26: ¿Cómo participa el equipo en mejorar la forma de trabajar? | G26: =IF(D26="","",MATCH(D26,Config!$B$21:$E$21,0)-1) | H26: =IF(E26="","",MATCH(E26,Config!$B$21:$E$21,0)-1) | I26: =IF(F26="","",MATCH(F26,Config!$B$21:$E$21,0)-1) | J26: =IF(COUNT(G26:I26)<2,"",MAX(G26:I26)-MIN(G26:I26)) | K26: =IF(J26="","",IF(J26>=Config!$M$5,"Conversar",""))
B28: Promedio por área
B29: Área | D29: =D4 -> Persona 1 | E29: =E4 -> Persona 2 | F29: =F4 -> Persona 3
B30: Flujo y responsables | D30: =IFERROR(SUMIF($B$7:$B$26,$B30,G$7:G$26)/(COUNTIFS($B$7:$B$26,$B30,G$7:G$26,"<>")*3),"") -> 0 | E30: =IFERROR(SUMIF($B$7:$B$26,$B30,H$7:H$26)/(COUNTIFS($B$7:$B$26,$B30,H$7:H$26,"<>")*3),"") -> 0 | F30: =IFERROR(SUMIF($B$7:$B$26,$B30,I$7:I$26)/(COUNTIFS($B$7:$B$26,$B30,I$7:I$26,"<>")*3),"") -> 0
B31: Datos | D31: =IFERROR(SUMIF($B$7:$B$26,$B31,G$7:G$26)/(COUNTIFS($B$7:$B$26,$B31,G$7:G$26,"<>")*3),"") -> 0 | E31: =IFERROR(SUMIF($B$7:$B$26,$B31,H$7:H$26)/(COUNTIFS($B$7:$B$26,$B31,H$7:H$26,"<>")*3),"") -> 0 | F31: =IFERROR(SUMIF($B$7:$B$26,$B31,I$7:I$26)/(COUNTIFS($B$7:$B$26,$B31,I$7:I$26,"<>")*3),"") -> 0
B32: Excepciones y control | D32: =IFERROR(SUMIF($B$7:$B$26,$B32,G$7:G$26)/(COUNTIFS($B$7:$B$26,$B32,G$7:G$26,"<>")*3),"") -> 0 | E32: =IFERROR(SUMIF($B$7:$B$26,$B32,H$7:H$26)/(COUNTIFS($B$7:$B$26,$B32,H$7:H$26,"<>")*3),"") -> 0 | F32: =IFERROR(SUMIF($B$7:$B$26,$B32,I$7:I$26)/(COUNTIFS($B$7:$B$26,$B32,I$7:I$26,"<>")*3),"") -> 0
B33: Recursos y medición | D33: =IFERROR(SUMIF($B$7:$B$26,$B33,G$7:G$26)/(COUNTIFS($B$7:$B$26,$B33,G$7:G$26,"<>")*3),"") -> 0 | E33: =IFERROR(SUMIF($B$7:$B$26,$B33,H$7:H$26)/(COUNTIFS($B$7:$B$26,$B33,H$7:H$26,"<>")*3),"") -> 0 | F33: =IFERROR(SUMIF($B$7:$B$26,$B33,I$7:I$26)/(COUNTIFS($B$7:$B$26,$B33,I$7:I$26,"<>")*3),"") -> 0
B34: Documentación y equipo | D34: =IFERROR(SUMIF($B$7:$B$26,$B34,G$7:G$26)/(COUNTIFS($B$7:$B$26,$B34,G$7:G$26,"<>")*3),"") -> 0 | E34: =IFERROR(SUMIF($B$7:$B$26,$B34,H$7:H$26)/(COUNTIFS($B$7:$B$26,$B34,H$7:H$26,"<>")*3),"") -> 0 | F34: =IFERROR(SUMIF($B$7:$B$26,$B34,I$7:I$26)/(COUNTIFS($B$7:$B$26,$B34,I$7:I$26,"<>")*3),"") -> 0
B36: «Conversar» aparece cuando dos personas están a 2 o más puntos de distancia en la misma pregunta.

Sheet Metodología
B2: Base metodológica
B4: Qué evalúa
B5: La pregunta central de Procesos Claros: ¿tiene la empresa reglas, datos y responsables suficientemente claros para que un software los ejecute? Un ERP no inventa reglas de negocio; las automatiza.
B7: Qué toma del 2025 Small Business Operations Report de ProcessDriven (4.740 equipos)
B8: 1. Formato de respuesta. Igual que el Systemization Snapshot, cada pregunta ofrece alternativas que describen situaciones concretas (por ejemplo: «nos detendríamos / tendríamos problemas / seguiríamos funcionando»), en vez de una escala genérica de frecuencia. Esto reduce la tendencia a responder de forma optimista.
B9: 2. Preguntas comparables. 10 de las 20 preguntas están adaptadas de preguntas del reporte (responsabilidades, tareas rutinarias, visibilidad del trabajo, uso de herramientas, imprevistos, manejo de errores, tiempo para mejorar, documentación, persona clave e ideas del equipo), lo que permite mostrar cómo responden otras pymes.
B10: 3. Estructura por categorías. Las áreas del test se corresponden con las tres categorías del reporte: Ejecución de tareas → Flujo y responsables; Asignación de recursos (tiempo, energía y presupuesto) → Recursos y medición y parte de Excepciones; Documentación del conocimiento → Documentación y equipo.
B11: 4. Tiempo reactivo vs. tiempo de mejora. Se incorpora la distinción del reporte entre trabajo reactivo, rutinario y de mejora: implementar un ERP es trabajo de mejora, y una empresa sin tiempo para mejorar difícilmente lo absorbe.
B12: 5. Registro de errores como primer sistema. El reporte lo recomienda como el primer sistema para empresas que viven apagando incendios; por eso es el «Paso 0» de todo resultado que no sea «Lista».
B13: 6. Criterios de documentación. La pregunta sobre procesos descritos usa los criterios del reporte: accesible, centralizado, editable y seguro.
B14: 7. Uso repetido. Como el Snapshot, el test está pensado para repetirse en el tiempo y compararse contra uno mismo.
B16: Qué agrega Procesos Claros para la preparación para un ERP
... B37: Procesos Claros — procesosclaros.cl/antes-del-erp.

Sheet Config
A1: N° | B1: 0 pts | C1: 1 pt | D1: 2 pts | E1: 3 pts | F1: Crítica | H1: Área | I1: Qué mide | J1: Primera acción | L1: Parámetro | M1: Valor
A2: 1 | B2: No: cada pedido sigue su propio camino | C2: Lo sabe el dueño o una persona, de memoria | D2: Está dibujado o escrito, pero incompleto o desactualizado | E2: Está dibujado de punta a punta y vigente | F2: 1 | H2: Flujo y responsables | I2: Quién hace qué, cuándo y cómo, desde que entra un cliente hasta que cobras. | J2: Toma un pedido real y dibuja en una hoja su recorrido completo, de la venta al cobro. Ponle a cada paso un responsable con nombre. | L2: Umbral 'Lista' (puntaje total) | M2: 0.7
A3: 2 | B3: Todos hacen de todo | C3: Se sabe por costumbre, pero no está escrito | D3: Hay responsables escritos solo para algunas etapas | E3: Cada etapa tiene un responsable con nombre, por escrito | F3: 1 | H3: Datos | I3: Si la información existe una sola vez, es confiable, está en un lugar oficial y las herramientas se usan de verdad. | J3: Define una sola lista oficial de productos, clientes y precios, con un responsable. Depura duplicados y retira las copias personales en Excel. | L3: Umbral 'Zona intermedia' (puntaje total) | M3: 0.45
A4: 3 | B4: De memoria | C4: Cada persona con su propia lista o recordatorio | D4: En un lugar compartido, pero solo en algunas áreas | E4: Todas en un lugar compartido, con frecuencia y responsable | F4: 0 | H4: Excepciones y control | I4: Qué pasa cuando algo sale mal, cada cuánto pasa, y si los errores se previenen. | J4: Escribe en una página qué hacer en las 3 situaciones que más se repiten (devolución, quiebre de stock, pedido urgente) y quién decide en cada caso. | L4: Mínimo por área para 'Lista' | M4: 0.5
A5: 4 | B5: Preguntándole a alguien | C5: Revisando varios lugares (Excel, WhatsApp, correo) | D5: En un solo lugar, pero no siempre al día | E5: En un solo lugar, al día, sin preguntarle a nadie | F5: 0 | H5: Recursos y medición | I5: Dónde se van el tiempo y el dinero: márgenes, caja, indicadores y tiempo para mejorar. | J5: Arma un flujo de caja simple a 13 semanas, calcula el margen de tus 10 productos más vendidos y reserva 2 horas semanales del equipo para mejoras. | L5: Diferencia entre personas que se marca para conversar | M5: 2
A6: 5 | B6: En varios Excel personales, cada uno con su versión | C6: Hay una lista principal, pero conviven copias y duplicados | D6: Hay una lista única, con algunos duplicados o datos incompletos | E6: En una sola fuente, con códigos únicos y un responsable de mantenerla | F6: 1 | H6: Documentación y equipo | I6: Si la operación funciona sin depender de una persona y el equipo participa en el cambio. | J6: Identifica las 3 tareas que solo sabe hacer una persona y documenta cada una en un instructivo de una página, en un lugar compartido.
A7: 6 | B7: No sabemos: no se revisa | C7: Hay diferencias frecuentes que nadie explica | D7: Hay diferencias menores y se explican | E7: Coincide, y se verifica con conteos periódicos | F7: 0 | L7: Supuestos de Procesos Claros, ajustables. Ver hoja Metodología.
A8: 7 | B8: Tres veces o más, en distintas planillas o sistemas | C8: Dos veces | D8: Una vez, con algunas excepciones | E8: Una sola vez; después se consulta, no se copia | F8: 0
A9: 8 | B9: No hay herramientas compartidas: cada uno con lo suyo | C9: Existen, pero pocos las usan o están desactualizadas | D9: La mayoría las usa, pero en paralelo hay Excel o cuadernos propios | E9: Todo el equipo las usa y la información está al día | F9: 0
A10: 9 | B10: Se improvisa cada vez | C10: Depende de quién esté | D10: Hay una forma acordada, pero no escrita | E10: Hay una forma acordada, escrita y conocida por todos | F10: 1
A11: 10 | B11: A diario | C11: Varias veces por semana | D11: Algunas veces al mes | E11: Rara vez | F11: 0
A12: 11 | B12: Buscamos un culpable o lo dejamos pasar | C12: Lo arreglamos y seguimos | D12: Lo arreglamos y tomamos una acción para que no se repita | E12: Lo arreglamos, lo registramos y tomamos una acción para que no se repita | F12: 0
A13: 12 | B13: No existen | C13: Existen, pero se saltan con frecuencia | D13: Existen y casi siempre se respetan | E13: Están escritos, se respetan y se revisan | F13: 0
A14: 13 | B14: No | C14: Tenemos una idea general | D14: Para los principales productos o servicios | E14: Para todos, y se actualiza cuando cambian costos o precios | F14: 0
A15: 14 | B15: Miramos el saldo del banco | C15: Proyectamos solo cuando hay un problema | D15: Proyectamos a 3 meses o más, pero no lo revisamos seguido | E15: Flujo a 3+ meses revisado seguido, que incluye inventario y cuentas por cobrar | F15: 0
A16: 15 | B16: Ninguno | C16: Solo ventas | D16: Algunos operativos, sin meta ni responsable | E16: 3 a 5 operativos, con meta y responsable, revisados periódicamente | F16: 0
A17: 16 | B17: Apagando incendios: arreglando errores y reclamos | C17: En el trabajo rutinario; nunca queda tiempo para mejorar | D17: En el trabajo rutinario, y de vez en cuando mejoramos algo | E17: En el trabajo rutinario, con tiempo reservado para mejorar | F17: 0
A18: 17 | B18: No están descritos: viven en la cabeza de las personas | C18: En archivos dispersos, difíciles de encontrar | D18: En un solo lugar, pero desactualizados o sin control de acceso | E18: En un solo lugar, accesibles, actualizados y con acceso controlado | F18: 0
A19: 18 | B19: Se detendría | C19: Tendría problemas serios | D19: Haría lo esencial, con dificultad | E19: Seguiría funcionando con normalidad | F19: 0
... A21: 20 | B21: No participa | C21: Se le informa de los cambios | D21: Se le consulta de vez en cuando | E21: Participa en definir procesos y hay un lugar donde se registran sus ideas | F21: 0
